{"cameraMode":{"drawMode":0,"name":"Shaded","section":"Shading Mode"},"sceneLighting":true,"audioPlay":false,"sceneViewState":{"m_AlwaysRefresh":false,"showFog":true,"showSkybox":true,"showFlares":true,"showImageEffects":true,"showParticleSystems":true,"showVisualEffectGraphs":true,"m_FxEnabled":true},"in2DMode":false,"pivot":{"x":-3.2735986709594728,"y":6.658339500427246,"z":14.701236724853516},"rotation":{"x":0.09583156555891037,"y":-0.02090182900428772,"z":0.002012728713452816,"w":0.995176374912262},"size":13.022601127624512,"orthographic":false}